m3u_extractor/__init__.py
m3u_extractor/fetcher.py
m3u_extractor/formatter.py
m3u_extractor/m3u_extractor.py
m3u_extractor/parser.py
m3u_extractor-0.1.1.dist-info/METADATA
m3u_extractor-0.1.1.dist-info/WHEEL
m3u_extractor-0.1.1.dist-info/RECORD
